markyp/__init__.py
markyp/elements.py
markyp/formatters.py
markyp/parser.py
markyp/py.typed
markyp/utils.py
markyp-0.2307.0.dist-info/LICENSE
markyp-0.2307.0.dist-info/METADATA
markyp-0.2307.0.dist-info/WHEEL
markyp-0.2307.0.dist-info/top_level.txt
markyp-0.2307.0.dist-info/RECORD
